airflow_providers_tm1/__init__.py
airflow_providers_tm1/hooks/__init__.py
airflow_providers_tm1/hooks/tm1.py
airflow_providers_tm1/operators/__init__.py
airflow_providers_tm1/operators/tm1_run_ti.py
airflow_providers_tm1/sensors/__init__.py
airflow_providers_tm1-0.0.10.dist-info/LICENSE
airflow_providers_tm1-0.0.10.dist-info/METADATA
airflow_providers_tm1-0.0.10.dist-info/WHEEL
airflow_providers_tm1-0.0.10.dist-info/entry_points.txt
airflow_providers_tm1-0.0.10.dist-info/top_level.txt
airflow_providers_tm1-0.0.10.dist-info/RECORD
