Metadata-Version: 2.1
Name: airflow-providers-tm1
Version: 0.0.10
Summary: A package to simplify connecting to the TM1 REST API from Apache Airflow
Author-email: KnowledgeSeed <info@knowledgeseed.ch>, Marius Wirtz <mwirtz@cubewise.com>, Alexander Sutcliffe <sutcliffe.alex@gmail.com>
Maintainer-email: Akos Andras Nagy <akos.nagy@knowledgeseed.ch>, Marius Wirtz <mwirtz@cubewise.com>
License: Apache License
Project-URL: Documentation, https://github.com/KnowledgeSeed/airflow-providers-tm1/blob/master/README.md
Project-URL: Repository, https://github.com/KnowledgeSeed/airflow-providers-tm1
Project-URL: Issues, https://github.com/KnowledgeSeed/airflow-providers-tm1/issues
Project-URL: Changelog, https://github.com/KnowledgeSeed/airflow-providers-tm1/CHANGELOG.md
Requires-Python: >=3.7
License-File: LICENSE
Requires-Dist: apache-airflow >=2.2
Requires-Dist: tm1py >=1.1
